mstm_studio/__init__.py
mstm_studio/__main__.py
mstm_studio/alloy_AuAg.py
mstm_studio/contrib_spheroid.py
mstm_studio/contributions.py
mstm_studio/diel_size_correction.py
mstm_studio/fit_spheres_optic.py
mstm_studio/mie_theory.py
mstm_studio/mstm_spectrum.py
mstm_studio/mstm_studio_gui.py
mstm_studio/mstm_studio_support.py
mstm_studio/nearfield.py
mstm_studio/rii_materials.py
mstm_studio/images/brush_icon&16.png
mstm_studio/images/chart_bar2_icon&16.png
mstm_studio/images/chart_bar_icon&16.png
mstm_studio/images/cogs_icon&16.png
mstm_studio/images/delete_icon&16.png
mstm_studio/images/doc_edit_icon&16.png
mstm_studio/images/export_icon&16.png
mstm_studio/images/folder_open_icon&16.png
mstm_studio/images/import_icon&16.png
mstm_studio/images/on-off_icon&16.png
mstm_studio/images/playback_play_icon&16.png
mstm_studio/images/playback_stop_icon&16.png
mstm_studio/images/refresh_icon&16.png
mstm_studio/images/round_minus_icon&16.png
mstm_studio/images/round_plus_icon&16.png
mstm_studio/images/save_icon&16.png
mstm_studio/images/splash.png
mstm_studio/images/sq_plus_icon&16.png
mstm_studio/nk/etaGold.txt
mstm_studio/nk/etaSilver.txt
mstm_studio/nk/etaWater.txt
mstm_studio-1.2.1.dist-info/licenses/LICENSE
mstm_studio-1.2.1.dist-info/METADATA
mstm_studio-1.2.1.dist-info/WHEEL
mstm_studio-1.2.1.dist-info/top_level.txt
mstm_studio-1.2.1.dist-info/RECORD
